{
    "results": [
        {
            "id": 1096010,
            "title": "Egg Salad Wrap",
            "image": "https://spoonacular.com/recipeImages/1096010-312x231.jpg",
            "imageType": "jpg",
            "like": 0
        },
        {
            "id": 642178,
            "title": "Egg and Dairy Free Pancakes",
            "image": "https://spoonacular.com/recipeImages/642178-312x231.jpg",
            "imageType": "jpg",
            "like": 0
        },
        {
            "id": 642246,
            "title": "Egg-Free Chocolate Cupcakes",
            "image": "https://spoonacular.com/recipeImages/642246-312x231.jpg",
            "imageType": "jpg",
            "like": 0
        },
        {
            "id": 642245,
            "title": "Egg-Free Cranberry Thumbprints",
            "image": "https://spoonacular.com/recipeImages/642245-312x231.jpg",
            "imageType": "jpg",
            "like": 0
        },
        {
            "id": 642240,
            "title": "Egg Salad Sandwiches With Tarragon",
            "image": "https://spoonacular.com/recipeImages/642240-312x231.jpg",
            "imageType": "jpg",
            "like": 1
        },
        {
            "id": 642230,
            "title": "Egg Souffle With Bacon and Asparagus",
            "image": "https://spoonacular.com/recipeImages/642230-312x231.jpg",
            "imageType": "jpg",
            "like": 0
        },
        {
            "id": 662744,
            "title": "Taco Egg Roll",
            "image": "https://spoonacular.com/recipeImages/662744-312x231.jpg",
            "imageType": "jpg",
            "like": 0
        },
        {
            "id": 645060,
            "title": "Good-Egg Salad Sandwich",
            "image": "https://spoonacular.com/recipeImages/645060-312x231.jpg",
            "imageType": "jpg",
            "like": 0
        },
        {
            "id": 641700,
            "title": "Duck Egg Omelette With Caviar and Sour Cream",
            "image": "https://spoonacular.com/recipeImages/641700-312x231.jpg",
            "imageType": "jpg",
            "like": 0
        },
        {
            "id": 633587,
            "title": "Baked Egg Linguine With Onion, Scallion, and Umame",
            "image": "https://spoonacular.com/recipeImages/633587-312x231.jpg",
            "imageType": "jpg",
            "like": 0
        },
        {
            "id": 716363,
            "title": "Scotch Egg",
            "image": "https://spoonacular.com/recipeImages/716363-312x231.jpg",
            "imageType": "jpg",
            "like": 0
        },
        {
            "id": 660094,
            "title": "Simple Egg Salad",
            "image": "https://spoonacular.com/recipeImages/660094-312x231.jpg",
            "imageType": "jpg",
            "like": 0
        },
        {
            "id": 635601,
            "title": "Boiled Egg Curry",
            "image": "https://spoonacular.com/recipeImages/635601-312x231.jpg",
            "imageType": "jpg",
            "like": 0
        },
        {
            "id": 640636,
            "title": "Creamy Egg Marinara Breakfast Dip",
            "image": "https://spoonacular.com/recipeImages/640636-312x231.jpg",
            "imageType": "jpg",
            "like": 0
        },
        {
            "id": 640638,
            "title": "Creamy egg-less chocolate ice cream with chocolate chip cookies",
            "image": "https://spoonacular.com/recipeImages/640638-312x231.jpg",
            "imageType": "jpg",
            "like": 0
        },
        {
            "id": 646833,
            "title": "Holiday Egg Nog",
            "image": "https://spoonacular.com/recipeImages/646833-312x231.jpg",
            "imageType": "jpg",
            "like": 0
        },
        {
            "id": 716245,
            "title": "Avocado Egg Salad",
            "image": "https://spoonacular.com/recipeImages/716245-312x231.jpg",
            "imageType": "jpg",
            "like": 0
        },
        {
            "id": 1512847,
            "title": "Avocado Egg Salad",
            "image": "https://spoonacular.com/recipeImages/1512847-312x231.jpg",
            "imageType": "jpg",
            "like": 0
        },
        {
            "id": 633264,
            "title": "Bacon & Egg Bouquets",
            "image": "https://spoonacular.com/recipeImages/633264-312x231.jpg",
            "imageType": "jpg",
            "like": 0
        },
        {
            "id": 633265,
            "title": "Bacon & Egg Toast Cups",
            "image": "https://spoonacular.com/recipeImages/633265-312x231.jpg",
            "imageType": "jpg",
            "like": 0
        },
        {
            "id": 656481,
            "title": "Poached Egg With Spinach and Tomato",
            "image": "https://spoonacular.com/recipeImages/656481-312x231.jpg",
            "imageType": "jpg",
            "like": 0
        },
        {
            "id": 769533,
            "title": "chettinad egg curry",
            "image": "https://spoonacular.com/recipeImages/769533-312x231.jpg",
            "imageType": "jpg",
            "like": 0
        },
        {
            "id": 1095775,
            "title": "Delicious Egg Custard",
            "image": "https://spoonacular.com/recipeImages/1095775-312x231.jpg",
            "imageType": "jpg",
            "like": 0
        },
        {
            "id": 660707,
            "title": "Southwest Egg Rolls with Cilantro Lime Pesto",
            "image": "https://spoonacular.com/recipeImages/660707-312x231.jpg",
            "imageType": "jpg",
            "like": 0
        },
        {
            "id": 653775,
            "title": "Open-Face Egg Sandwich with Bacon, Asparagus, and Pesto",
            "image": "https://spoonacular.com/recipeImages/653775-312x231.jpg",
            "imageType": "jpg",
            "like": 1
        },
        {
            "id": 659596,
            "title": "Scrambled Egg-Stuffed Poblano Chiles With Spicy Cheese Sauce",
            "image": "https://spoonacular.com/recipeImages/659596-312x231.jpg",
            "imageType": "jpg",
            "like": 0
        },
        {
            "id": 663338,
            "title": "The Scotch Egg",
            "image": "https://spoonacular.com/recipeImages/663338-312x231.jpg",
            "imageType": "jpg",
            "like": 0
        },
        {
            "id": 639320,
            "title": "Chorizo and egg bake",
            "image": "https://spoonacular.com/recipeImages/639320-312x231.jpg",
            "imageType": "jpg",
            "like": 0
        },
        {
            "id": 1096058,
            "title": "Sausage and Egg Breakfast Burrito",
            "image": "https://spoonacular.com/recipeImages/1096058-312x231.jpg",
            "imageType": "jpg",
            "like": 0
        },
        {
            "id": 1095895,
            "title": "Mini Quinoa Egg Breakfast Casserole",
            "image": "https://spoonacular.com/recipeImages/1095895-312x231.jpg",
            "imageType": "jpg",
            "like": 0
        },
        {
            "id": 646302,
            "title": "Hard-Boiled Egg Gratin In A Bechamel Sauce",
            "image": "https://spoonacular.com/recipeImages/646302-312x231.jpg",
            "imageType": "jpg",
            "like": 0
        },
        {
            "id": 652354,
            "title": "Monte Cristo Egg Rolls",
            "image": "https://spoonacular.com/recipeImages/652354-312x231.jpg",
            "imageType": "jpg",
            "like": 0
        },
        {
            "id": 1096274,
            "title": "Very Vanilla Egg-Free Ice Cream",
            "image": "https://spoonacular.com/recipeImages/1096274-312x231.jpg",
            "imageType": "jpg",
            "like": 0
        },
        {
            "id": 646545,
            "title": "Heart Shaped Egg & Cheese Nibbles",
            "image": "https://spoonacular.com/recipeImages/646545-312x231.jpg",
            "imageType": "jpg",
            "like": 0
        },
        {
            "id": 659906,
            "title": "Shrimp & Crab Egg Rolls",
            "image": "https://spoonacular.com/recipeImages/659906-312x231.jpg",
            "imageType": "jpg",
            "like": 0
        },
        {
            "id": 1096286,
            "title": "Bacon Wrapped Egg Cups with Horseradish and Cheddar",
            "image": "https://spoonacular.com/recipeImages/1096286-312x231.jpg",
            "imageType": "jpg",
            "like": 0
        },
        {
            "id": 639306,
            "title": "Simple Poached Egg Dinner",
            "image": "https://spoonacular.com/recipeImages/639306-312x231.jpg",
            "imageType": "jpg",
            "like": 0
        },
        {
            "id": 658290,
            "title": "Rice with Fried Egg and Sausage",
            "image": "https://spoonacular.com/recipeImages/658290-312x231.jpg",
            "imageType": "jpg",
            "like": 0
        },
        {
            "id": 1095962,
            "title": "Broccoli Cheddar Egg Cups for Breakfast",
            "image": "https://spoonacular.com/recipeImages/1095962-312x231.jpg",
            "imageType": "jpg",
            "like": 0
        },
        {
            "id": 1095777,
            "title": "Cheesy Bacon Sausage Egg Hash Brown Skillet",
            "image": "https://spoonacular.com/recipeImages/1095777-312x231.jpg",
            "imageType": "jpg",
            "like": 0
        },
        {
            "id": 657031,
            "title": "Potatoes Smothered with Egg Sauce (Cariucho)",
            "image": "https://spoonacular.com/recipeImages/657031-312x231.jpg",
            "imageType": "jpg",
            "like": 0
        },
        {
            "id": 658495,
            "title": "Roasted Asparagus with Egg Salad",
            "image": "https://spoonacular.com/recipeImages/658495-312x231.jpg",
            "imageType": "jpg",
            "like": 0
        },
        {
            "id": 1697489,
            "title": "3 Delicious Twists on an Egg Salad Sandwich",
            "image": "https://spoonacular.com/recipeImages/1697489-312x231.jpg",
            "imageType": "jpg",
            "like": 0
        },
        {
            "id": 636393,
            "title": "Buckwheat Galette With An Egg",
            "image": "https://spoonacular.com/recipeImages/636393-312x231.jpg",
            "imageType": "jpg",
            "like": 0
        },
        {
            "id": 659396,
            "title": "Sausage, Spinach, and Quail Egg Breakfast Salad",
            "image": "https://spoonacular.com/recipeImages/659396-312x231.jpg",
            "imageType": "jpg",
            "like": 0
        },
        {
            "id": 634421,
            "title": "Basil & Black Pepper Beef With Egg Noodles",
            "image": "https://spoonacular.com/recipeImages/634421-312x231.jpg",
            "imageType": "jpg",
            "like": 0
        },
        {
            "id": 660015,
            "title": "Shrimp Udon w Fish Cakes & Poached Egg",
            "image": "https://spoonacular.com/recipeImages/660015-312x231.jpg",
            "imageType": "jpg",
            "like": 0
        },
        {
            "id": 487193,
            "title": "Sweet Potato with Bacon and Poached Egg",
            "image": "https://spoonacular.com/recipeImages/487193-312x231.jpg",
            "imageType": "jpg",
            "like": 0
        },
        {
            "id": 991625,
            "title": "Nutella Buttercream Cupcakes with Hidden Cadbury Egg",
            "image": "https://spoonacular.com/recipeImages/991625-312x231.jpg",
            "imageType": "jpg",
            "like": 0
        },
        {
            "id": 715736,
            "title": "Eggs",
            "image": "https://spoonacular.com/recipeImages/715736-312x231.jpg",
            "imageType": "jpg",
            "like": 0
        },
        {
            "id": 659581,
            "title": "Scotch Eggs",
            "image": "https://spoonacular.com/recipeImages/659581-312x231.jpg",
            "imageType": "jpg",
            "like": 0
        },
        {
            "id": 1095996,
            "title": "Vegan Eggnog",
            "image": "https://spoonacular.com/recipeImages/1095996-312x231.jpg",
            "imageType": "jpg",
            "like": 0
        },
        {
            "id": 642283,
            "title": "Eggplant Curry",
            "image": "https://spoonacular.com/recipeImages/642283-312x231.jpg",
            "imageType": "jpg",
            "like": 0
        },
        {
            "id": 664748,
            "title": "Veggie Meatloaf",
            "image": "https://spoonacular.com/recipeImages/664748-312x231.jpg",
            "imageType": "jpg",
            "like": 0
        },
        {
            "id": 642332,
            "title": "Eggs Florentine",
            "image": "https://spoonacular.com/recipeImages/642332-312x231.jpg",
            "imageType": "jpg",
            "like": 0
        },
        {
            "id": 642254,
            "title": "Eggless Brownies",
            "image": "https://spoonacular.com/recipeImages/642254-312x231.jpg",
            "imageType": "jpg",
            "like": 0
        },
        {
            "id": 642325,
            "title": "Eggplant Parmesan",
            "image": "https://spoonacular.com/recipeImages/642325-312x231.jpg",
            "imageType": "jpg",
            "like": 0
        },
        {
            "id": 642293,
            "title": "Eggplant Parmesan",
            "image": "https://spoonacular.com/recipeImages/642293-312x231.jpg",
            "imageType": "jpg",
            "like": 0
        },
        {
            "id": 634785,
            "title": "Beet Pickled Eggs",
            "image": "https://spoonacular.com/recipeImages/634785-312x231.jpg",
            "imageType": "jpg",
            "like": 0
        },
        {
            "id": 642303,
            "title": "Eggplant pizzette",
            "image": "https://spoonacular.com/recipeImages/642303-312x231.jpg",
            "imageType": "jpg",
            "like": 0
        },
        {
            "id": 641472,
            "title": "Deviled Quail Eggs",
            "image": "https://spoonacular.com/recipeImages/641472-312x231.jpg",
            "imageType": "jpg",
            "like": 0
        },
        {
            "id": 660404,
            "title": "Smoky Deviled Eggs",
            "image": "https://spoonacular.com/recipeImages/660404-312x231.jpg",
            "imageType": "jpg",
            "like": 0
        },
        {
            "id": 642347,
            "title": "Eggy In The Basket",
            "image": "https://spoonacular.com/recipeImages/642347-312x231.jpg",
            "imageType": "jpg",
            "like": 0
        },
        {
            "id": 1095997,
            "title": "Rum & Eggnog Latte",
            "image": "https://spoonacular.com/recipeImages/1095997-312x231.jpg",
            "imageType": "jpg",
            "like": 0
        },
        {
            "id": 647627,
            "title": "Hummus Deviled Eggs",
            "image": "https://spoonacular.com/recipeImages/647627-312x231.jpg",
            "imageType": "jpg",
            "like": 0
        },
        {
            "id": 661447,
            "title": "Square Deviled Eggs",
            "image": "https://spoonacular.com/recipeImages/661447-312x231.jpg",
            "imageType": "jpg",
            "like": 0
        },
        {
            "id": 641958,
            "title": "Easy Eggplant Curry",
            "image": "https://spoonacular.com/recipeImages/641958-312x231.jpg",
            "imageType": "jpg",
            "like": 0
        },
        {
            "id": 651956,
            "title": "Mini eggplant pizza",
            "image": "https://spoonacular.com/recipeImages/651956-312x231.jpg",
            "imageType": "jpg",
            "like": 0
        },
        {
            "id": 650239,
            "title": "Loaded Veggie Omelet",
            "image": "https://spoonacular.com/recipeImages/650239-312x231.jpg",
            "imageType": "jpg",
            "like": 0
        },
        {
            "id": 652059,
            "title": "Miso Eggplant Gratin",
            "image": "https://spoonacular.com/recipeImages/652059-312x231.jpg",
            "imageType": "jpg",
            "like": 0
        },
        {
            "id": 653918,
            "title": "Orange Miso Eggplant",
            "image": "https://spoonacular.com/recipeImages/653918-312x231.jpg",
            "imageType": "jpg",
            "like": 0
        },
        {
            "id": 639594,
            "title": "Classic Eggs Benedict",
            "image": "https://spoonacular.com/recipeImages/639594-312x231.jpg",
            "imageType": "jpg",
            "like": 0
        },
        {
            "id": 648351,
            "title": "Jalapeno Deviled Eggs",
            "image": "https://spoonacular.com/recipeImages/648351-312x231.jpg",
            "imageType": "jpg",
            "like": 0
        },
        {
            "id": 157960,
            "title": "Portobello Baked Eggs",
            "image": "https://spoonacular.com/recipeImages/157960-312x231.jpg",
            "imageType": "jpg",
            "like": 0
        },
        {
            "id": 1096067,
            "title": "Portobello Baked Eggs",
            "image": "https://spoonacular.com/recipeImages/1096067-312x231.jpg",
            "imageType": "jpg",
            "like": 0
        },
        {
            "id": 661967,
            "title": "Stuffed Baby Eggplant",
            "image": "https://spoonacular.com/recipeImages/661967-312x231.jpg",
            "imageType": "jpg",
            "like": 0
        },
        {
            "id": 641461,
            "title": "Deviled Eggs With Crab",
            "image": "https://spoonacular.com/recipeImages/641461-312x231.jpg",
            "imageType": "jpg",
            "like": 0
        },
        {
            "id": 646982,
            "title": "Meatless Eggs Benedict",
            "image": "https://spoonacular.com/recipeImages/646982-312x231.jpg",
            "imageType": "jpg",
            "like": 0
        },
        {
            "id": 664697,
            "title": "Vegetarian Scotch Eggs",
            "image": "https://spoonacular.com/recipeImages/664697-312x231.jpg",
            "imageType": "jpg",
            "like": 0
        },
        {
            "id": 641962,
            "title": "Easy Eggplant Parmesan",
            "image": "https://spoonacular.com/recipeImages/641962-312x231.jpg",
            "imageType": "jpg",
            "like": 0
        },
        {
            "id": 651407,
            "title": "Mediterranean eggplants",
            "image": "https://spoonacular.com/recipeImages/651407-312x231.jpg",
            "imageType": "jpg",
            "like": 0
        },
        {
            "id": 632928,
            "title": "Asparagus Eggs Benedict",
            "image": "https://spoonacular.com/recipeImages/632928-312x231.jpg",
            "imageType": "jpg",
            "like": 1
        },
        {
            "id": 658573,
            "title": "Roasted Eggplant Hummus",
            "image": "https://spoonacular.com/recipeImages/658573-312x231.jpg",
            "imageType": "jpg",
            "like": 0
        },
        {
            "id": 656486,
            "title": "Poached eggs in tomatoes",
            "image": "https://spoonacular.com/recipeImages/656486-312x231.jpg",
            "imageType": "jpg",
            "like": 0
        },
        {
            "id": 640275,
            "title": "Crab Cakes Eggs Benedict",
            "image": "https://spoonacular.com/recipeImages/640275-312x231.jpg",
            "imageType": "jpg",
            "like": 0
        },
        {
            "id": 658743,
            "title": "Roll Up Eggplant Lasagna",
            "image": "https://spoonacular.com/recipeImages/658743-312x231.jpg",
            "imageType": "jpg",
            "like": 0
        },
        {
            "id": 661094,
            "title": "Spicy Eggplant Spaghetti",
            "image": "https://spoonacular.com/recipeImages/661094-312x231.jpg",
            "imageType": "jpg",
            "like": 0
        },
        {
            "id": 632849,
            "title": "Asian Marinated Eggplant",
            "image": "https://spoonacular.com/recipeImages/632849-312x231.jpg",
            "imageType": "jpg",
            "like": 0
        },
        {
            "id": 632884,
            "title": "Asian Soft Scrambled Eggs",
            "image": "https://spoonacular.com/recipeImages/632884-312x231.jpg",
            "imageType": "jpg",
            "like": 0
        },
        {
            "id": 636458,
            "title": "Bunny Eggs Kids Breakfast",
            "image": "https://spoonacular.com/recipeImages/636458-312x231.jpg",
            "imageType": "jpg",
            "like": 0
        },
        {
            "id": 642276,
            "title": "Eggplant and Tomato Sauce",
            "image": "https://spoonacular.com/recipeImages/642276-312x231.jpg",
            "imageType": "jpg",
            "like": 0
        },
        {
            "id": 645706,
            "title": "Grilled Eggplant Sandwich",
            "image": "https://spoonacular.com/recipeImages/645706-312x231.jpg",
            "imageType": "jpg",
            "like": 0
        },
        {
            "id": 647876,
            "title": "Indian-Style Eggs On Toast",
            "image": "https://spoonacular.com/recipeImages/647876-312x231.jpg",
            "imageType": "jpg",
            "like": 0
        },
        {
            "id": 641890,
            "title": "Easy Cheesy Scrambled Eggs",
            "image": "https://spoonacular.com/recipeImages/641890-312x231.jpg",
            "imageType": "jpg",
            "like": 0
        },
        {
            "id": 642255,
            "title": "Eggless Chocolate Brownies",
            "image": "https://spoonacular.com/recipeImages/642255-312x231.jpg",
            "imageType": "jpg",
            "like": 0
        },
        {
            "id": 642297,
            "title": "Eggplant Parmesan Roll-Ups",
            "image": "https://spoonacular.com/recipeImages/642297-312x231.jpg",
            "imageType": "jpg",
            "like": 0
        },
        {
            "id": 634781,
            "title": "Beet Greens and Poached Eggs",
            "image": "https://spoonacular.com/recipeImages/634781-312x231.jpg",
            "imageType": "jpg",
            "like": 0
        },
        {
            "id": 639456,
            "title": "Cinnamon Eggless Coffee Cake",
            "image": "https://spoonacular.com/recipeImages/639456-312x231.jpg",
            "imageType": "jpg",
            "like": 0
        },
        {
            "id": 642264,
            "title": "Eggless Ginger & Mango Bread",
            "image": "https://spoonacular.com/recipeImages/642264-312x231.jpg",
            "imageType": "jpg",
            "like": 0
        },
        {
            "id": 716218,
            "title": "Tomato and Eggplant Caponata",
            "image": "https://spoonacular.com/recipeImages/716218-312x231.jpg",
            "imageType": "jpg",
            "like": 0
        }
    ]
}